setup.cfg
setup.py
useful_collections/__init__.py
useful_collections/dict.py
useful_collections/discoveries.py
useful_collections.egg-info/PKG-INFO
useful_collections.egg-info/SOURCES.txt
useful_collections.egg-info/dependency_links.txt
useful_collections.egg-info/top_level.txt