Metadata-Version: 1.1
Name: useful-collections
Version: 0.2
Summary: Useful collections for manipulate data in Python
Home-page: https://github.com/samukasmk/python-useful-collections
Author: Samuel Sampaio
Author-email: samuel@smk.net.br
License: Apache2
Download-URL: https://github.com/samukasmk/python-useful-collections/tarball/0.1
Keywords: collections,dict,immutable,immutability,lock,data,modules,class
Platform: UNKNOWN
Classifier: Development Status :: 3 - Alpha
Classifier: Intended Audience :: Developers
Classifier: License :: OSI Approved :: Apache Software License
Classifier: Programming Language :: Python :: 2
Classifier: Programming Language :: Python :: 2.6
Classifier: Programming Language :: Python :: 2.7
Classifier: Programming Language :: Python :: 3
Classifier: Programming Language :: Python :: 3.2
Classifier: Programming Language :: Python :: 3.3
Classifier: Programming Language :: Python :: 3.4
Classifier: Topic :: Utilities
